image_checker/DaliChecker.py
image_checker/__init__.py
image_checker/checker.py
image_checker/cli.py
image_checker/iterators.py
image_checker/logging_config.json
image_checker-0.27.3.dist-info/LICENSE
image_checker-0.27.3.dist-info/METADATA
image_checker-0.27.3.dist-info/WHEEL
image_checker-0.27.3.dist-info/entry_points.txt
image_checker-0.27.3.dist-info/top_level.txt
image_checker-0.27.3.dist-info/RECORD
