Metadata-Version: 2.1
Name: image-checker
Version: 0.27.3
Summary: Check for corrupted images using Nvidia DALI
Home-page: UNKNOWN
Author: Ceyda Cinarel
Author-email: snu-ceyda@users.noreply.github.com
License: MIT
Project-URL: repository, https://github.com/cceyda/image-checker
Keywords: image checker image integrity checker
Platform: UNKNOWN
Requires-Python: ==3.*,>=3.5.0
Requires-Dist: more-itertools (==8.*,>=8.6.0)
Requires-Dist: tqdm (==4.*,>=4.51.0)
